reader/__init__.py
reader/__main__.py
reader/_cli.py
reader/_config.py
reader/_hash_utils.py
reader/_types.py
reader/_update.py
reader/_utils.py
reader/core.py
reader/exceptions.py
reader/py.typed
reader/types.py
reader/utils.py
reader/_app/__init__.py
reader/_app/api_thing.py
reader/_app/cli.py
reader/_app/wsgi.py
reader/_app/static/controls.js
reader/_app/static/style.css
reader/_app/templates/add_entry.html
reader/_app/templates/entries.html
reader/_app/templates/entry.html
reader/_app/templates/feeds.html
reader/_app/templates/layout.html
reader/_app/templates/macros.html
reader/_app/templates/metadata.html
reader/_app/templates/tags.html
reader/_app/v2/__init__.py
reader/_app/v2/forms.py
reader/_app/v2/static/style.css
reader/_app/v2/static/theme.js
reader/_app/v2/templates/v2/entries.html
reader/_app/v2/templates/v2/layout.html
reader/_app/v2/templates/v2/macros.html
reader/_parser/__init__.py
reader/_parser/_http_utils.py
reader/_parser/_lazy.py
reader/_parser/_url_utils.py
reader/_parser/feedparser.py
reader/_parser/file.py
reader/_parser/http.py
reader/_parser/jsonfeed.py
reader/_parser/requests/__init__.py
reader/_parser/requests/_lazy.py
reader/_plugins/__init__.py
reader/_plugins/cli_status.py
reader/_plugins/enclosure_tags.py
reader/_plugins/preview_feed_list.py
reader/_plugins/share.py
reader/_plugins/sqlite_releases.py
reader/_plugins/timer.py
reader/_plugins/templates/preview_feed_list.html
reader/_storage/__init__.py
reader/_storage/_base.py
reader/_storage/_changes.py
reader/_storage/_entries.py
reader/_storage/_feeds.py
reader/_storage/_html_utils.py
reader/_storage/_schema.py
reader/_storage/_search.py
reader/_storage/_sql_utils.py
reader/_storage/_sqlite_utils.py
reader/_storage/_tags.py
reader/_vendor/__init__.py
reader/_vendor/feedparser/__init__.py
reader/_vendor/feedparser/api.py
reader/_vendor/feedparser/encodings.py
reader/_vendor/feedparser/exceptions.py
reader/_vendor/feedparser/html.py
reader/_vendor/feedparser/http.py
reader-3.19.dist-info/licenses/LICENSE
reader-3.19.dist-info/METADATA
reader-3.19.dist-info/WHEEL
reader-3.19.dist-info/top_level.txt
reader-3.19.dist-info/RECORD
