Metadata-Version: 2.4
Name: reader
Version: 3.19
Summary: A Python feed reader library.
Author: lemon24
License: BSD-3-Clause
Project-URL: Documentation, https://reader.readthedocs.io/
Project-URL: Repository, https://github.com/lemon24/reader
Project-URL: Issues, https://github.com/lemon24/reader/issues
Project-URL: Changelog, https://reader.readthedocs.io/en/latest/changelog.html
Keywords: atom,cdf,feed,rdf,rss,json feed,web feed,podcast,feed reader,feed aggregator
Classifier: Development Status :: 5 - Production/Stable
Classifier: Environment :: Console
Classifier: Environment :: Web Environment
Classifier: Intended Audience :: Developers
Classifier: Intended Audience :: End Users/Desktop
Classifier: License :: OSI Approved :: BSD License
Classifier: Operating System :: OS Independent
Classifier: Programming Language :: Python
Classifier: Programming Language :: Python :: 3
Classifier: Programming Language :: Python :: 3 :: Only
Classifier: Programming Language :: Python :: 3.11
Classifier: Programming Language :: Python :: 3.12
Classifier: Programming Language :: Python :: 3.13
Classifier: Programming Language :: Python :: 3.14
Classifier: Programming Language :: Python :: Implementation :: CPython
Classifier: Programming Language :: Python :: Implementation :: PyPy
Classifier: Topic :: Internet
Classifier: Topic :: Internet :: WWW/HTTP :: Dynamic Content :: News/Diary
Classifier: Topic :: Internet :: WWW/HTTP :: Indexing/Search
Classifier: Topic :: Internet :: WWW/HTTP :: WSGI :: Application
Classifier: Topic :: Software Development :: Libraries
Classifier: Topic :: Utilities
Classifier: Typing :: Typed
Requires-Python: >=3.11
License-File: LICENSE
Requires-Dist: typing-extensions>=4
Requires-Dist: feedparser>=6
Requires-Dist: requests>=2.18
Requires-Dist: werkzeug>2
Requires-Dist: iso8601>=1
Requires-Dist: beautifulsoup4>=4.5
Provides-Extra: all
Requires-Dist: reader[app,cli,unstable-plugins]; extra == "all"
Provides-Extra: cli
Requires-Dist: click>=7; extra == "cli"
Requires-Dist: PyYAML; extra == "cli"
Provides-Extra: app
Requires-Dist: flask>=0.10; extra == "app"
Requires-Dist: humanize>=4; extra == "app"
Requires-Dist: PyYAML; extra == "app"
Requires-Dist: WTForms; extra == "app"
Requires-Dist: jinja2-fragments; extra == "app"
Provides-Extra: unstable-plugins
Requires-Dist: requests; extra == "unstable-plugins"
Requires-Dist: mutagen; extra == "unstable-plugins"
Requires-Dist: requests; extra == "unstable-plugins"
Requires-Dist: beautifulsoup4; extra == "unstable-plugins"
Requires-Dist: blinker>=1.4; extra == "unstable-plugins"
Requires-Dist: beautifulsoup4; extra == "unstable-plugins"
Requires-Dist: tabulate; extra == "unstable-plugins"
Dynamic: license-file
